oximachinerunner/__init__.py
oximachinerunner/_version.py
oximachinerunner/_widget.py
oximachinerunner/config.py
oximachinerunner/errors.py
oximachinerunner/utils.py
oximachinerunner/widget.py
oximachinerunner/learnmofox/__init__.py
oximachinerunner/learnmofox/utils.py
test/__init__.py
test/test_oximachine.py
oximachinerunner-1.4.0.dist-info/LICENSE
oximachinerunner-1.4.0.dist-info/METADATA
oximachinerunner-1.4.0.dist-info/WHEEL
oximachinerunner-1.4.0.dist-info/top_level.txt
oximachinerunner-1.4.0.dist-info/RECORD
