Metadata-Version: 2.1
Name: oximachinerunner
Version: 1.4.0
Summary: Run the oximachine
Home-page: https://github.com/kjappelbaum/oximachinerunner
Author: Kevin M. Jablonka, Daniele Ongari, Mohamad Moosavi, Berend Smit
Author-email: kevin.jablonka@epfl.ch
License: MIT
Platform: UNKNOWN
Classifier: License :: OSI Approved :: GNU General Public License v3 (GPLv3)
Classifier: Topic :: Scientific/Engineering :: Chemistry
Classifier: Development Status :: 3 - Alpha
Classifier: Intended Audience :: Science/Research
Classifier: Programming Language :: Python
Classifier: Programming Language :: Python :: 3
Classifier: Programming Language :: Python :: 3.7
Classifier: Programming Language :: Python :: 3.8
Requires-Python: >=3.7,<3.9
Requires-Dist: oximachine-featurizer (>=0.3.1)
Requires-Dist: xgboost (~=1.3.3)
Provides-Extra: dev
Requires-Dist: pre-commit (~=2.6.0) ; extra == 'dev'
Requires-Dist: pylint (~=2.5.3) ; extra == 'dev'
Requires-Dist: pytest (~=6.0.1) ; extra == 'dev'
Requires-Dist: versioneer (~=0.18) ; extra == 'dev'
Requires-Dist: isort (~=4.3.21) ; extra == 'dev'
Requires-Dist: black ; extra == 'dev'
Provides-Extra: docs
Requires-Dist: sphinx (~=3.3.1) ; extra == 'docs'
Requires-Dist: sphinx-book-theme (~=0.0.39) ; extra == 'docs'
Requires-Dist: sphinx-autodoc-typehints (~=1.11.1) ; extra == 'docs'
Requires-Dist: sphinx-copybutton (~=0.3.1) ; extra == 'docs'
